dk_analyzer/__init__.py
dk_analyzer/graph_plotter.py
dk_analyzer/main.py
dk_analyzer/models.py
dk_analyzer/version.py
dk_analyzer/warcraftlogs.py
dk_analyzer-0.0.3.dist-info/METADATA
dk_analyzer-0.0.3.dist-info/WHEEL
dk_analyzer-0.0.3.dist-info/entry_points.txt
dk_analyzer-0.0.3.dist-info/top_level.txt
dk_analyzer-0.0.3.dist-info/RECORD
