Metadata-Version: 2.1
Name: dk-analyzer
Version: 0.0.3
Summary: Dk Analyzer
Home-page: https://github.com/nymann/dk-analyzer
Maintainer: Kristian Nymann Jakobsen
Maintainer-email: kristian@nymann.dev
Requires-Python: >=3.9
Requires-Dist: typer (>=0.4.1)
Requires-Dist: requests
Requires-Dist: matplotlib
Provides-Extra: all
Requires-Dist: add-trailing-comma ; extra == 'all'
Requires-Dist: python-dotenv ; extra == 'all'
Requires-Dist: black ; extra == 'all'
Requires-Dist: isort ; extra == 'all'
Requires-Dist: mypy ; extra == 'all'
Requires-Dist: nitpick ; extra == 'all'
Requires-Dist: wemake-python-styleguide ; extra == 'all'
Requires-Dist: types-requests ; extra == 'all'
Requires-Dist: pytest ; extra == 'all'
Requires-Dist: pytest-cov ; extra == 'all'
Requires-Dist: pytest-mock ; extra == 'all'
Provides-Extra: dev
Requires-Dist: add-trailing-comma ; extra == 'dev'
Requires-Dist: python-dotenv ; extra == 'dev'
Requires-Dist: black ; extra == 'dev'
Requires-Dist: isort ; extra == 'dev'
Requires-Dist: mypy ; extra == 'dev'
Requires-Dist: nitpick ; extra == 'dev'
Requires-Dist: wemake-python-styleguide ; extra == 'dev'
Requires-Dist: types-requests ; extra == 'dev'
Provides-Extra: package
Requires-Dist: twine ; extra == 'package'
Requires-Dist: wheel ; extra == 'package'
Provides-Extra: tests
Requires-Dist: pytest ; extra == 'tests'
Requires-Dist: pytest-cov ; extra == 'tests'
Requires-Dist: pytest-mock ; extra == 'tests'
